fluidsynth.py
pyfluidsynth_nowarnings-1.2.5.dist-info/LICENSE
pyfluidsynth_nowarnings-1.2.5.dist-info/METADATA
pyfluidsynth_nowarnings-1.2.5.dist-info/WHEEL
pyfluidsynth_nowarnings-1.2.5.dist-info/top_level.txt
pyfluidsynth_nowarnings-1.2.5.dist-info/RECORD
