Metadata-Version: 2.1
Name: pyfluidsynth-nowarnings
Version: 1.2.5
Summary: Python bindings for FluidSynth, a MIDI synthesizer that uses SoundFont instruments
Home-page: https://github.com/nwhitehead/pyfluidsynth
Author: Nathan Whitehead
Author-email: nwhitehe@gmail.com
License: UNKNOWN
Platform: UNKNOWN
Requires-Dist: future
